aifori/__init__.py
aifori/agent.py
aifori/api.py
aifori/buffer.py
aifori/client.py
aifori/config.py
aifori/core.py
aifori/db.py
aifori/memory.py
aifori/music.py
aifori/rule.py
aifori/session.py
aifori/task.py
aifori/util.py
aifori-0.0.3.dist-info/LICENSE
aifori-0.0.3.dist-info/METADATA
aifori-0.0.3.dist-info/WHEEL
aifori-0.0.3.dist-info/top_level.txt
aifori-0.0.3.dist-info/zip-safe
aifori-0.0.3.dist-info/RECORD
