Metadata-Version: 2.1
Name: aifori
Version: 0.0.3
Summary: aifori
Home-page: https://github.com/jerrychen1990/Aifori
Author: Chen Hao
Author-email: jerrychen1990@gmail.com
License: MIT
License-File: LICENSE
Requires-Dist: requests
Requires-Dist: pydantic
Requires-Dist: loguru
Requires-Dist: python-dotenv
Requires-Dist: fastapi
Requires-Dist: uvicorn
Requires-Dist: liteai
Requires-Dist: python-snippets
Requires-Dist: streamlit
Requires-Dist: mem0ai
Requires-Dist: sqlalchemy
Requires-Dist: click
Requires-Dist: pydub
Requires-Dist: celery
Requires-Dist: redis
Requires-Dist: gtts
Requires-Dist: python-multipart
